rocket/__init__.py
rocket/rocket.py
rocketAouaichia/__init__.py
rocketAouaichia/rocket.py
rocketAouaichia-0.1.dist-info/LICENSE.txt
rocketAouaichia-0.1.dist-info/METADATA
rocketAouaichia-0.1.dist-info/WHEEL
rocketAouaichia-0.1.dist-info/top_level.txt
rocketAouaichia-0.1.dist-info/RECORD
